botz/__init__.py
botz/bot/__init__.py
botz/bot/brain/__init__.py
botz/bot/eyes/__init__.py
botz/bot/feet/__init__.py
botz/bot/hands/__init__.py
ctxs/__init__.py
ctxs/dbs/__init__.py
pybotz-0.0.1.dist-info/LICENSE
pybotz-0.0.1.dist-info/METADATA
pybotz-0.0.1.dist-info/WHEEL
pybotz-0.0.1.dist-info/top_level.txt
pybotz-0.0.1.dist-info/RECORD
