Metadata-Version: 2.1
Name: pybotz
Version: 0.0.1
Summary: rpa open source package
Home-page: https://github.com/qool-dat/pybotz
Author: qool dat
Author-email: qool.dat@gmail.com
License: UNKNOWN
Project-URL: Bug Tracker, https://github.com/qool-dat/pybotz/issues
Platform: UNKNOWN
Classifier: Programming Language :: Python :: 3
Classifier: License :: OSI Approved :: MIT License
Classifier: Operating System :: OS Independent
Requires-Python: >=3.6
License-File: LICENSE
